cmaboss/cmaboss.cp311-win32.pyd
cmaboss/__init__.py
cmaboss-1.0.0b31.dist-info/DELVEWHEEL
cmaboss-1.0.0b31.dist-info/METADATA
cmaboss-1.0.0b31.dist-info/RECORD
cmaboss-1.0.0b31.dist-info/WHEEL
cmaboss.libs/iconv-2-98e4f1f2e7da8f22706d656155a21984.dll
cmaboss.libs/libsbml-4982dc2d9cd6768465647f18c1996ef9.dll
cmaboss.libs/libxml2-a836cb95131c1ca0a2b7a968e23a94cb.dll
cmaboss.libs/msvcp140-97e71a3c697fb1ab3af777db39009e46.dll
cmaboss.libs/zlib1-253b55ffca1ae0abfb0b38964f395755.dll
cmaboss_1024n/cmaboss_1024n.cp311-win32.pyd
cmaboss_1024n/__init__.py
cmaboss_128n/cmaboss_128n.cp311-win32.pyd
cmaboss_128n/__init__.py
cmaboss_256n/cmaboss_256n.cp311-win32.pyd
cmaboss_256n/__init__.py
cmaboss_512n/cmaboss_512n.cp311-win32.pyd
cmaboss_512n/__init__.py
cmaboss_dn/cmaboss_dn.cp311-win32.pyd
cmaboss_dn/__init__.py
