Metadata-Version: 2.2
Name: cmaboss
Version: 1.0.0b31
Summary: Python wrapper for MaBoSS
